LICENSE
README.md
setup.py
NlpToolkit_ParseTree.egg-info/PKG-INFO
NlpToolkit_ParseTree.egg-info/SOURCES.txt
NlpToolkit_ParseTree.egg-info/dependency_links.txt
NlpToolkit_ParseTree.egg-info/requires.txt
NlpToolkit_ParseTree.egg-info/top_level.txt
ParseTree/ConstituentSpan.py
ParseTree/NodeCollector.py
ParseTree/ParallelTreeBank.py
ParseTree/ParseNode.py
ParseTree/ParseTree.py
ParseTree/SearchDirectionType.py
ParseTree/Symbol.py
ParseTree/TreeBank.py
ParseTree/__init__.py
ParseTree/NodeCondition/IsEnglishLeaf.py
ParseTree/NodeCondition/IsLeaf.py
ParseTree/NodeCondition/NodeCondition.py
ParseTree/NodeCondition/__init__.py