Metadata-Version: 2.1
Name: NlpToolkit-ParseTree
Version: 1.0.12
Summary: Constituency Parse Tree Library
Home-page: https://github.com/StarlangSoftware/ParseTree-Py
Author: olcaytaner
Author-email: olcay.yildiz@ozyegin.edu.tr
License: UNKNOWN
Platform: UNKNOWN
License-File: LICENSE
